prompt_composer-0.1.0.dist-info/METADATA
prompt_composer-0.1.0.dist-info/WHEEL
prompt_composer-0.1.0.dist-info/licenses/LICENSE
prompt_composer/__init__.py
prompt_composer/_prompt_composer.cpython-312-x86_64-linux-gnu.so
prompt_composer/prompts/behaviors/planning.md
prompt_composer/prompts/behaviors/progress.md
prompt_composer/prompts/behaviors/reasoning.md
prompt_composer/prompts/behaviors/tools.md
prompt_composer/prompts/domains/analysis.md
prompt_composer/prompts/domains/filesystem.md
prompt_composer/prompts/domains/programming.md
prompt_composer/prompts/domains/system.md
prompt_composer/prompts/server_patterns.toml
prompt_composer-0.1.0.dist-info/RECORD
