Metadata-Version: 2.4
Name: prompt-composer
Version: 0.1.0
Classifier: Development Status :: 3 - Alpha
Classifier: Intended Audience :: Developers
Classifier: License :: OSI Approved :: MIT License
Classifier: Programming Language :: Python :: 3
Classifier: Programming Language :: Python :: 3.8
Classifier: Programming Language :: Python :: 3.9
Classifier: Programming Language :: Python :: 3.10
Classifier: Programming Language :: Python :: 3.11
Classifier: Programming Language :: Python :: 3.12
Classifier: Programming Language :: Rust
Classifier: Topic :: Software Development :: Libraries :: Python Modules
Classifier: Topic :: Scientific/Engineering :: Artificial Intelligence
License-File: LICENSE
Summary: A modular system prompt composition framework for AI assistants
Keywords: ai,llm,prompt,mcp,tools
Author: Ben Vierck
License: MIT
Requires-Python: >=3.8
Project-URL: Homepage, https://github.com/xcud/prompt-composer
Project-URL: Repository, https://github.com/xcud/prompt-composer
Project-URL: Documentation, https://github.com/xcud/prompt-composer#readme
Project-URL: Issues, https://github.com/xcud/prompt-composer/issues
